ImgGameLib/__init__.py
ImgGameLib/canvas.py
ImgGameLib/constants.py
ImgGameLib/drawable.py
ImgGameLib/rectangle.py
ImgGameLib/sprite.py
ImgGameLib-0.2.1.dist-info/LICENSE
ImgGameLib-0.2.1.dist-info/METADATA
ImgGameLib-0.2.1.dist-info/WHEEL
ImgGameLib-0.2.1.dist-info/top_level.txt
ImgGameLib-0.2.1.dist-info/RECORD
