Metadata-Version: 2.1
Name: ImgGameLib
Version: 0.2.1
Summary: A lightweight wrapper around pillow for making games with images
Home-page: https://github.com/aaguy-hue/ImgGameLib
Author: aaguy-hue
Author-email: aaditmathur6.extra@gmail.com
License: UNKNOWN
Project-URL: Bug Tracker, https://github.com/aaguy-hue/ImgGameLib/issues
Platform: UNKNOWN
Classifier: Topic :: Software Development :: User Interfaces
Classifier: Intended Audience :: Developers
Classifier: License :: OSI Approved :: GNU General Public License v3 (GPLv3)
Classifier: Operating System :: OS Independent
Classifier: Programming Language :: Python :: 3.7
Classifier: Programming Language :: Python :: 3.8
Classifier: Programming Language :: Python :: 3.9
Classifier: Programming Language :: Python :: 3.10
Classifier: Programming Language :: Python :: 3.11
Requires-Python: >=3.7
Requires-Dist: pillow
